STIFMaps/STIFMap_generation.py
STIFMaps/__init__.py
STIFMaps/misc.py
STIFMaps/training.py
STIFMaps/vis.py
stifmaps-0.0.8.dist-info/METADATA
stifmaps-0.0.8.dist-info/WHEEL
stifmaps-0.0.8.dist-info/licenses/LICENSE
stifmaps-0.0.8.dist-info/RECORD
