Metadata-Version: 2.4
Name: STIFMaps
Version: 0.0.8
Summary: STIFMaps predicts the local stiffness of breast tissue using the morphology of collagen
Project-URL: Homepage, https://github.com/cstashko/STIFMaps
Project-URL: Bug Tracker, https://github.com/cstashko/STIFMaps/issues
Author-email: Connor Stashko <cstashko@berkeley.edu>
License-Expression: MIT
License-File: LICENSE
Classifier: License :: OSI Approved :: MIT License
Classifier: Operating System :: OS Independent
Classifier: Programming Language :: Python :: 3
Requires-Python: >=3.7
Requires-Dist: jupyter>=1.0.0
Requires-Dist: matplotlib>=3.5.3
Requires-Dist: numpy>=1.21.6
Requires-Dist: opencv-python>=4.6.0.66
Requires-Dist: pandas>=1.3.5
Requires-Dist: scikit-image>=0.19.3
Requires-Dist: scikit-learn>=1.0.2
Requires-Dist: scipy>=1.7.3
Requires-Dist: seaborn>=0.11.2
Requires-Dist: torch>=1.10.2
Requires-Dist: torchvision>=0.11.3
Requires-Dist: tqdm>=4.64.0
Requires-Dist: xlrd>=2.0.1
